{"layers": [{"name": "ZeroPadding3D", "custom_name": "zeropadding3d", "trainable": true, "input_shape": [1, 16, 32, 32], "padding": [0, 1, 1], "cache_enabled": true}, {"len_conv_dim3": 3, "W_constraint": null, "b_constraint": null, "name": "Convolution3D", "custom_name": "LGN", "len_conv_dim1": 1, "activation": "relu", "trainable": true, "dim_ordering": "th", "subsample": [1, 1, 1], "cache_enabled": true, "init": "glorot_uniform", "nb_filter": 4, "len_conv_dim2": 3, "b_regularizer": null, "W_regularizer": {"l2": 0.001, "name": "WeightRegularizer", "l1": 0.0}, "activity_regularizer": null, "border_mode": "valid"}, {"name": "BatchNormalization", "custom_name": "batchnormalization", "epsilon": 1e-06, "trainable": true, "cache_enabled": true, "mode": 0, "momentum": 0.9, "axis": -1}, {"name": "MaxPooling3D", "custom_name": "maxpooling3d", "strides": [1, 2, 2], "trainable": true, "dim_ordering": "th", "pool_size": [1, 2, 2], "cache_enabled": true, "border_mode": "valid"}, {"padding": [1, 1, 1], "cache_enabled": true, "trainable": true, "name": "ZeroPadding3D", "custom_name": "zeropadding3d"}, {"len_conv_dim3": 3, "W_constraint": null, "b_constraint": null, "name": "Convolution3D", "custom_name": "V1", "len_conv_dim1": 3, "activation": "relu", "trainable": true, "dim_ordering": "th", "subsample": [1, 1, 1], "cache_enabled": true, "init": "glorot_uniform", "nb_filter": 4, "len_conv_dim2": 3, "b_regularizer": null, "W_regularizer": {"l2": 0.001, "name": "WeightRegularizer", "l1": 0.0}, "activity_regularizer": null, "border_mode": "valid"}, {"name": "BatchNormalization", "custom_name": "batchnormalization", "epsilon": 1e-06, "trainable": true, "cache_enabled": true, "mode": 0, "momentum": 0.9, "axis": -1}, {"name": "MaxPooling3D", "custom_name": "maxpooling3d", "strides": [2, 2, 2], "trainable": true, "dim_ordering": "th", "pool_size": [2, 2, 2], "cache_enabled": true, "border_mode": "valid"}, {"len_conv_dim3": 3, "W_constraint": null, "b_constraint": null, "name": "Convolution3D", "custom_name": "MT", "len_conv_dim1": 3, "activation": "relu", "trainable": true, "dim_ordering": "th", "subsample": [1, 1, 1], "cache_enabled": true, "init": "glorot_uniform", "nb_filter": 4, "len_conv_dim2": 3, "b_regularizer": null, "W_regularizer": {"l2": 0.001, "name": "WeightRegularizer", "l1": 0.0}, "activity_regularizer": null, "border_mode": "valid"}, {"name": "BatchNormalization", "custom_name": "batchnormalization", "epsilon": 1e-06, "trainable": true, "cache_enabled": true, "mode": 0, "momentum": 0.9, "axis": -1}, {"cache_enabled": true, "trainable": true, "name": "Flatten", "custom_name": "flatten"}, {"W_constraint": null, "b_constraint": null, "name": "Dense", "custom_name": "dense", "activity_regularizer": null, "trainable": true, "cache_enabled": true, "init": "normal", "activation": "linear", "input_dim": null, "b_regularizer": null, "W_regularizer": {"l2": 0.001, "name": "WeightRegularizer", "l1": 0.0}, "output_dim": 8}, {"cache_enabled": true, "activation": "softmax", "trainable": true, "name": "Activation", "custom_name": "activation"}], "loss": "categorical_crossentropy", "optimizer": {"epsilon": 1e-06, "lr": 0.0010000000474974513, "name": "RMSprop", "rho": 0.8999999761581421}, "name": "Sequential", "class_mode": "categorical", "sample_weight_mode": null}